aalpy/__init__.py
aalpy/paths.py
aalpy/SULs/AutomataSUL.py
aalpy/SULs/PyMethodSUL.py
aalpy/SULs/RegexSUL.py
aalpy/SULs/TomitaSUL.py
aalpy/SULs/__init__.py
aalpy/automata/Dfa.py
aalpy/automata/MarkovChain.py
aalpy/automata/Mdp.py
aalpy/automata/MealyMachine.py
aalpy/automata/MooreMachine.py
aalpy/automata/NonDeterministicMooreMachine.py
aalpy/automata/Onfsm.py
aalpy/automata/Sevpa.py
aalpy/automata/StochasticMealyMachine.py
aalpy/automata/Vpa.py
aalpy/automata/__init__.py
aalpy/base/Automaton.py
aalpy/base/CacheTree.py
aalpy/base/Oracle.py
aalpy/base/SUL.py
aalpy/base/__init__.py
aalpy/learning_algs/__init__.py
aalpy/learning_algs/adaptive/AdaptiveLSharp.py
aalpy/learning_algs/adaptive/AdaptiveObservationTree.py
aalpy/learning_algs/adaptive/StateMatching.py
aalpy/learning_algs/adaptive/__init__.py
aalpy/learning_algs/deterministic/ADS.py
aalpy/learning_algs/deterministic/Apartness.py
aalpy/learning_algs/deterministic/ClassificationTree.py
aalpy/learning_algs/deterministic/CounterExampleProcessing.py
aalpy/learning_algs/deterministic/KV.py
aalpy/learning_algs/deterministic/LSharp.py
aalpy/learning_algs/deterministic/LStar.py
aalpy/learning_algs/deterministic/ObservationTable.py
aalpy/learning_algs/deterministic/ObservationTree.py
aalpy/learning_algs/deterministic/__init__.py
aalpy/learning_algs/deterministic_passive/ClassicRPNI.py
aalpy/learning_algs/deterministic_passive/GsmRPNI.py
aalpy/learning_algs/deterministic_passive/PAPNI.py
aalpy/learning_algs/deterministic_passive/RPNI.py
aalpy/learning_algs/deterministic_passive/__init__.py
aalpy/learning_algs/deterministic_passive/active_RPNI.py
aalpy/learning_algs/deterministic_passive/rpni_helper_functions.py
aalpy/learning_algs/general_passive/GeneralizedStateMerging.py
aalpy/learning_algs/general_passive/GsmAlgorithms.py
aalpy/learning_algs/general_passive/GsmNode.py
aalpy/learning_algs/general_passive/Instrumentation.py
aalpy/learning_algs/general_passive/ScoreFunctionsGSM.py
aalpy-1.5.2.dist-info/METADATA
aalpy-1.5.2.dist-info/WHEEL
aalpy-1.5.2.dist-info/top_level.txt
aalpy-1.5.2.dist-info/RECORD
