Metadata-Version: 2.1
Name: aalpy
Version: 1.5.2
Summary: An active automata learning library
Home-page: https://github.com/DES-Lab/AALpy
Author: Edi Muskardin
Author-email: edi.muskardin@silicon-austria.com
License: MIT
Classifier: Programming Language :: Python :: 3
Classifier: License :: OSI Approved :: MIT License
Classifier: Operating System :: OS Independent
Requires-Python: >=3.6
Requires-Dist: pydot
